8Mux_Using_2Mux/2Mux_behavioural.v
module Mux_21 (
    input wire v0,
    input wire v1,
    input wire x,
    output reg z
);

    always @ (*)begin
       if (x == 0) begin
           z = v0;
       end
       if (x == 1)begin
           z = v1;
        end
    end

endmodule

8Mux_Using_2Mux/8Mux_using_2Mux.v
module Mux_81 (
    input wire[7:0] data,
    input wire a2,
    input wire a1,
    input wire a0,
    output reg y
);
    wire z1,z2,z3,z4,z5,z6,z7;

    Mux_21 Mux_21_1(data[7], data[6], a0, z1);
    Mux_21 Mux_21_2(data[5], data[4], a0, z2);
    Mux_21 Mux_21_3(data[3], data[2], a0, z3); 
    Mux_21 Mux_21_4(data[1], data[0], a0, z4);

    Mux_21 Mux_21_5(z1, z2, a1, z5);
    Mux_21 Mux_21_6(z3, z4, a1, z6);

    Mux_21 Mux_21_7(z5, z6, a2, z7);

    always @ (z7)  begin
        y=z7;
    end
    
endmodule

8Mux_Using_2Mux/t_8Mux_using_2Mux.v
`timescale 1ns/100ps

module t_mux();
    reg[2:0] a;
    reg[7:0] data;
    wire y;

    Mux_81 Multiplexer_8_1 (data, a[2], a[1], a[0], y);

    always @* begin
        #100;
        a <= a + 1;
    end

    initial begin
        $dumpfile("8_mux.vcd");
        $dumpvars();

        data <= 8'b10100101;

        a <= 3'b000;
        $monitor("%d, %b %b %b , %b", $time, a[2], a[1], a[0], y);
        #799;

        $finish;
    end
endmodule

8Mux_Using_2Mux/8_mux.vcd
$date
	Sun Feb 21 10:05:13 2021
$end
$version
	Icarus Verilog
$end
$timescale
	100ps
$end
$scope module t_mux $end
$var wire 1 ! y $end
$var reg 3 " a [2:0] $end
$var reg 8 # data [7:0] $end
$scope module Multiplexer_8_1 $end
$var wire 1 $ a0 $end
$var wire 1 % a1 $end
$var wire 1 & a2 $end
$var wire 8 ' data [7:0] $end
$var wire 1 ( z7 $end
$var wire 1 ) z6 $end
$var wire 1 * z5 $end
$var wire 1 + z4 $end
$var wire 1 , z3 $end
$var wire 1 - z2 $end
$var wire 1 . z1 $end
$var reg 1 ! y $end
$scope module Mux_21_1 $end
$var wire 1 / v0 $end
$var wire 1 0 v1 $end
$var wire 1 $ x $end
$var reg 1 . z $end
$upscope $end
$scope module Mux_21_2 $end
$var wire 1 1 v0 $end
$var wire 1 2 v1 $end
$var wire 1 $ x $end
$var reg 1 - z $end
$upscope $end
$scope module Mux_21_3 $end
$var wire 1 3 v0 $end
$var wire 1 4 v1 $end
$var wire 1 $ x $end
$var reg 1 , z $end
$upscope $end
$scope module Mux_21_4 $end
$var wire 1 5 v0 $end
$var wire 1 6 v1 $end
$var wire 1 $ x $end
$var reg 1 + z $end
$upscope $end
$scope module Mux_21_5 $end
$var wire 1 . v0 $end
$var wire 1 - v1 $end
$var wire 1 % x $end
$var reg 1 * z $end
$upscope $end
$scope module Mux_21_6 $end
$var wire 1 , v0 $end
$var wire 1 + v1 $end
$var wire 1 % x $end
$var reg 1 ) z $end
$upscope $end
$scope module Mux_21_7 $end
$var wire 1 * v0 $end
$var wire 1 ) v1 $end
$var wire 1 & x $end
$var reg 1 ( z $end
$upscope $end
$upscope $end
$upscope $end
$enddefinitions $end
#0
$dumpvars
16
05
14
03
02
11
00
1/
1.
1-
0,
0+
1*
0)
1(
b10100101 '
0&
0%
0$
b10100101 #
b0 "
1!
$end
#1000
0!
0(
0*
1)
0.
0-
1,
1+
1$
b1 "
#2000
1!
1(
1*
0)
1.
1-
0,
0+
1%
0$
b10 "
#3000
0!
0(
0*
1)
0.
0-
1,
1+
1$
b11 "
#4000
1*
0)
1.
1-
0,
0+
1&
0%
0$
b100 "
#5000
1!
1(
0*
1)
0.
0-
1,
1+
1$
b101 "
#6000
0!
0(
1*
0)
1.
1-
0,
0+
1%
0$
b110 "
#7000
1!
1(
0*
1)
0.
0-
1,
1+
1$
b111 "
