Barrel_Shifter/sor_left.v
module sor_left(
    input wire[7:0] data,
    input wire[2:0] select,
    input wire control,
    output reg[7:0] sor
);
    integer i,j;
    reg[7:0] barrel;

    always@(control) begin
        barrel = data;
        for(j=1;j<=select;j = j+1 ) begin
            for(i=7 ; i>0; i = i -1) begin
                barrel[i]<= barrel[i-1];
                barrel[0]<= barrel[7];
            end
        #1;
        end
            
        //sor = (control<1)? (data << select): barrel;
        if (control == 0)begin
            sor = data<<select;
        end else begin
            sor = barrel;
        end
        
    end
endmodule

Barrel_Shifter/t_barrel_shifter.v
`timescale 1ns/100ps

module t_shift_left_rotate_left();
    reg[7:0] data;
    wire[7:0] sor;
    reg[2:0] select;
    //control = 0: shift left; control = 1: rotate left
    reg control;

    //shifter/rotator
    sor_left sl_1(.data(data), .select(select), .control(control), .sor(sor));

    initial begin
        $dumpfile("shift_rotate.vcd");
        $dumpvars();

        //data to be shifted/rotated
        data <= 8'b10100110;

        //amount of shift/rotation
        select <= 3'b110;

        //shift left
        control<= 0;
        #100;

        //rotate left
        control <= 1;
        #100;
        $finish;
    end
endmodule

Barrel_Shifter/shift_rotate.vcd
$date
	Thu Feb 25 22:17:57 2021
$end
$version
	Icarus Verilog
$end
$timescale
	100ps
$end
$scope module t_shift_left_rotate_left $end
$var wire 8 ! sor [7:0] $end
$var reg 1 " control $end
$var reg 8 # data [7:0] $end
$var reg 3 $ select [2:0] $end
$scope module sl_1 $end
$var wire 1 " control $end
$var wire 8 % data [7:0] $end
$var wire 3 & select [2:0] $end
$var reg 8 ' barrel [7:0] $end
$var reg 8 ( sor [7:0] $end
$var integer 32 ) i [31:0] $end
$var integer 32 * j [31:0] $end
$upscope $end
$upscope $end
$enddefinitions $end
#0
$dumpvars
b1 *
b0 )
bx (
b1001101 '
b110 &
b10100110 %
b110 $
b10100110 #
0"
bx !
$end
#10
b10011010 '
b0 )
b10 *
#20
b110101 '
b0 )
b11 *
#30
b1101010 '
b0 )
b100 *
#40
b11010100 '
b0 )
b101 *
#50
b10101001 '
b0 )
b110 *
#60
b10000000 !
b10000000 (
b111 *
#1000
b0 )
b1 *
b1001101 '
1"
#1010
b10011010 '
b0 )
b10 *
#1020
b110101 '
b0 )
b11 *
#1030
b1101010 '
b0 )
b100 *
#1040
b11010100 '
b0 )
b101 *
#1050
b10101001 '
b0 )
b110 *
#1060
b10101001 !
b10101001 (
b111 *
